{
	"meta_info": {
		"dataset_name": "halpe26",
		"num_keypoints": 26,
		"keypoint_id2name": {
			"0": "nose",
			"1": "left_eye",
			"2": "right_eye",
			"3": "left_ear",
			"4": "right_ear",
			"5": "left_shoulder",
			"6": "right_shoulder",
			"7": "left_elbow",
			"8": "right_elbow",
			"9": "left_wrist",
			"10": "right_wrist",
			"11": "left_hip",
			"12": "right_hip",
			"13": "left_knee",
			"14": "right_knee",
			"15": "left_ankle",
			"16": "right_ankle",
			"17": "head",
			"18": "neck",
			"19": "hip",
			"20": "left_big_toe",
			"21": "right_big_toe",
			"22": "left_small_toe",
			"23": "right_small_toe",
			"24": "left_heel",
			"25": "right_heel"
		},
		"keypoint_name2id": {
			"nose": 0,
			"left_eye": 1,
			"right_eye": 2,
			"left_ear": 3,
			"right_ear": 4,
			"left_shoulder": 5,
			"right_shoulder": 6,
			"left_elbow": 7,
			"right_elbow": 8,
			"left_wrist": 9,
			"right_wrist": 10,
			"left_hip": 11,
			"right_hip": 12,
			"left_knee": 13,
			"right_knee": 14,
			"left_ankle": 15,
			"right_ankle": 16,
			"head": 17,
			"neck": 18,
			"hip": 19,
			"left_big_toe": 20,
			"right_big_toe": 21,
			"left_small_toe": 22,
			"right_small_toe": 23,
			"left_heel": 24,
			"right_heel": 25
		},
		"upper_body_ids": [
			0,
			1,
			2,
			3,
			4,
			5,
			6,
			7,
			8,
			9,
			10,
			17,
			18
		],
		"lower_body_ids": [
			11,
			12,
			13,
			14,
			15,
			16,
			19,
			20,
			21,
			22,
			23,
			24,
			25
		],
		"flip_indices": [
			0,
			2,
			1,
			4,
			3,
			6,
			5,
			8,
			7,
			10,
			9,
			12,
			11,
			14,
			13,
			16,
			15,
			17,
			18,
			19,
			21,
			20,
			23,
			22,
			25,
			24
		],
		"flip_pairs": [
			[
				2,
				1
			],
			[
				1,
				2
			],
			[
				4,
				3
			],
			[
				3,
				4
			],
			[
				6,
				5
			],
			[
				5,
				6
			],
			[
				8,
				7
			],
			[
				7,
				8
			],
			[
				10,
				9
			],
			[
				9,
				10
			],
			[
				12,
				11
			],
			[
				11,
				12
			],
			[
				14,
				13
			],
			[
				13,
				14
			],
			[
				16,
				15
			],
			[
				15,
				16
			],
			[
				21,
				20
			],
			[
				20,
				21
			],
			[
				23,
				22
			],
			[
				22,
				23
			],
			[
				25,
				24
			],
			[
				24,
				25
			]
		],
		"keypoint_colors": {
			"__ndarray__": [
				[
					51,
					153,
					255
				],
				[
					51,
					153,
					255
				],
				[
					51,
					153,
					255
				],
				[
					51,
					153,
					255
				],
				[
					51,
					153,
					255
				],
				[
					0,
					255,
					0
				],
				[
					255,
					128,
					0
				],
				[
					0,
					255,
					0
				],
				[
					255,
					128,
					0
				],
				[
					0,
					255,
					0
				],
				[
					255,
					128,
					0
				],
				[
					0,
					255,
					0
				],
				[
					255,
					128,
					0
				],
				[
					0,
					255,
					0
				],
				[
					255,
					128,
					0
				],
				[
					0,
					255,
					0
				],
				[
					255,
					128,
					0
				],
				[
					255,
					128,
					0
				],
				[
					255,
					128,
					0
				],
				[
					255,
					128,
					0
				],
				[
					255,
					128,
					0
				],
				[
					255,
					128,
					0
				],
				[
					255,
					128,
					0
				],
				[
					255,
					128,
					0
				],
				[
					255,
					128,
					0
				],
				[
					255,
					128,
					0
				]
			],
			"dtype": "uint8",
			"shape": [
				26,
				3
			],
			"Corder": true
		},
		"num_skeleton_links": 27,
		"skeleton_links": [
			[
				15,
				13
			],
			[
				13,
				11
			],
			[
				11,
				19
			],
			[
				16,
				14
			],
			[
				14,
				12
			],
			[
				12,
				19
			],
			[
				17,
				18
			],
			[
				18,
				19
			],
			[
				18,
				5
			],
			[
				5,
				7
			],
			[
				7,
				9
			],
			[
				18,
				6
			],
			[
				6,
				8
			],
			[
				8,
				10
			],
			[
				1,
				2
			],
			[
				0,
				1
			],
			[
				0,
				2
			],
			[
				1,
				3
			],
			[
				2,
				4
			],
			[
				3,
				5
			],
			[
				4,
				6
			],
			[
				15,
				20
			],
			[
				15,
				22
			],
			[
				15,
				24
			],
			[
				16,
				21
			],
			[
				16,
				23
			],
			[
				16,
				25
			]
		],
		"skeleton_link_colors": {
			"__ndarray__": [
				[
					0,
					255,
					0
				],
				[
					0,
					255,
					0
				],
				[
					0,
					255,
					0
				],
				[
					255,
					128,
					0
				],
				[
					255,
					128,
					0
				],
				[
					255,
					128,
					0
				],
				[
					51,
					153,
					255
				],
				[
					51,
					153,
					255
				],
				[
					0,
					255,
					0
				],
				[
					0,
					255,
					0
				],
				[
					0,
					255,
					0
				],
				[
					255,
					128,
					0
				],
				[
					255,
					128,
					0
				],
				[
					255,
					128,
					0
				],
				[
					51,
					153,
					255
				],
				[
					51,
					153,
					255
				],
				[
					51,
					153,
					255
				],
				[
					51,
					153,
					255
				],
				[
					51,
					153,
					255
				],
				[
					51,
					153,
					255
				],
				[
					51,
					153,
					255
				],
				[
					0,
					255,
					0
				],
				[
					0,
					255,
					0
				],
				[
					0,
					255,
					0
				],
				[
					255,
					128,
					0
				],
				[
					255,
					128,
					0
				],
				[
					255,
					128,
					0
				]
			],
			"dtype": "uint8",
			"shape": [
				27,
				3
			],
			"Corder": true
		},
		"dataset_keypoint_weights": {
			"__ndarray__": [
				1.0,
				1.0,
				1.0,
				1.0,
				1.0,
				1.0,
				1.0,
				1.2000000476837158,
				1.2000000476837158,
				1.5,
				1.5,
				1.0,
				1.0,
				1.2000000476837158,
				1.2000000476837158,
				1.5,
				1.5,
				1.0,
				1.0,
				1.2000000476837158,
				1.5,
				1.5,
				1.5,
				1.5,
				1.5,
				1.5
			],
			"dtype": "float32",
			"shape": [
				26
			]
		},
		"sigmas": {
			"__ndarray__": [
				0.026000000536441803,
				0.02500000037252903,
				0.02500000037252903,
				0.03500000014901161,
				0.03500000014901161,
				0.07900000363588333,
				0.07900000363588333,
				0.07199999690055847,
				0.07199999690055847,
				0.06199999898672104,
				0.06199999898672104,
				0.10700000077486038,
				0.10700000077486038,
				0.08699999749660492,
				0.08699999749660492,
				0.08900000154972076,
				0.08900000154972076,
				0.026000000536441803,
				0.026000000536441803,
				0.06599999964237213,
				0.07900000363588333,
				0.07900000363588333,
				0.07900000363588333,
				0.07900000363588333,
				0.07900000363588333,
				0.07900000363588333
			],
			"dtype": "float32",
			"shape": [
				26
			]
		}
	},
	"instance_info": [
		{
			"frame_id": 1,
			"instances": [
				{
					"keypoints": [
						[
							811.6690063476562,
							195.33880615234375
						],
						[
							805.6683959960938,
							172.5363311767578
						],
						[
							793.6670532226562,
							185.73776245117188
						],
						[
							840.47216796875,
							125.73126220703125
						],
						[
							833.2713623046875,
							134.13217163085938
						],
						[
							929.2817993164062,
							149.73387145996094
						],
						[
							926.8815307617188,
							188.13803100585938
						],
						[
							848.873046875,
							300.95025634765625
						],
						[
							894.47802734375,
							341.75469970703125
						],
						[
							732.46044921875,
							378.9587097167969
						],
						[
							792.4669799804688,
							404.1614685058594
						],
						[
							1118.90234375,
							372.95806884765625
						],
						[
							1075.6976318359375,
							365.7572937011719
						],
						[
							959.2850341796875,
							531.375244140625
						],
						[
							929.2817993164062,
							479.7696533203125
						],
						[
							1118.90234375,
							686.1920166015625
						],
						[
							964.0855712890625,
							678.9912719726562
						],
						[
							761.2635498046875,
							117.33035278320312
						],
						[
							895.6781616210938,
							164.1354217529297
						],
						[
							1098.5001220703125,
							353.7559814453125
						],
						[
							1052.8951416015625,
							769.0010375976562
						],
						[
							872.8756713867188,
							716.1953125
						],
						[
							1086.498779296875,
							764.2005004882812
						],
						[
							883.6768188476562,
							712.5949096679688
						],
						[
							1151.305908203125,
							711.394775390625
						],
						[
							983.2876586914062,
							713.7950439453125
						]
					],
					"keypoint_scores": [
						1.0099620819091797,
						1.0368114709854126,
						1.0473737716674805,
						1.1507456302642822,
						0.9014003872871399,
						0.9670441150665283,
						1.0352208614349365,
						1.0702619552612305,
						0.9530870914459229,
						1.0629855394363403,
						0.8281747102737427,
						1.0372929573059082,
						0.9266854524612427,
						1.0713980197906494,
						1.0958515405654907,
						1.1366475820541382,
						1.1069340705871582,
						0.9660490155220032,
						1.0597782135009766,
						1.099816083908081,
						0.7880294322967529,
						0.9608299732208252,
						1.0920255184173584,
						1.0440497398376465,
						1.0908033847808838,
						0.9901483654975891
					],
					"bbox": [
						[
							667.80517578125,
							58.283935546875,
							1183.5576171875,
							795.6439208984375
						]
					],
					"bbox_score": 0.8633556962013245
				}
			]
		}
	]
}