{
	"meta_info": {
		"dataset_name": "coco",
		"num_keypoints": 17,
		"keypoint_id2name": {
			"0": "nose",
			"1": "left_eye",
			"2": "right_eye",
			"3": "left_ear",
			"4": "right_ear",
			"5": "left_shoulder",
			"6": "right_shoulder",
			"7": "left_elbow",
			"8": "right_elbow",
			"9": "left_wrist",
			"10": "right_wrist",
			"11": "left_hip",
			"12": "right_hip",
			"13": "left_knee",
			"14": "right_knee",
			"15": "left_ankle",
			"16": "right_ankle"
		},
		"keypoint_name2id": {
			"nose": 0,
			"left_eye": 1,
			"right_eye": 2,
			"left_ear": 3,
			"right_ear": 4,
			"left_shoulder": 5,
			"right_shoulder": 6,
			"left_elbow": 7,
			"right_elbow": 8,
			"left_wrist": 9,
			"right_wrist": 10,
			"left_hip": 11,
			"right_hip": 12,
			"left_knee": 13,
			"right_knee": 14,
			"left_ankle": 15,
			"right_ankle": 16
		},
		"upper_body_ids": [
			0,
			1,
			2,
			3,
			4,
			5,
			6,
			7,
			8,
			9,
			10
		],
		"lower_body_ids": [
			11,
			12,
			13,
			14,
			15,
			16
		],
		"flip_indices": [
			0,
			2,
			1,
			4,
			3,
			6,
			5,
			8,
			7,
			10,
			9,
			12,
			11,
			14,
			13,
			16,
			15
		],
		"flip_pairs": [
			[
				2,
				1
			],
			[
				1,
				2
			],
			[
				4,
				3
			],
			[
				3,
				4
			],
			[
				6,
				5
			],
			[
				5,
				6
			],
			[
				8,
				7
			],
			[
				7,
				8
			],
			[
				10,
				9
			],
			[
				9,
				10
			],
			[
				12,
				11
			],
			[
				11,
				12
			],
			[
				14,
				13
			],
			[
				13,
				14
			],
			[
				16,
				15
			],
			[
				15,
				16
			]
		],
		"keypoint_colors": {
			"__ndarray__": [
				[
					51,
					153,
					255
				],
				[
					51,
					153,
					255
				],
				[
					51,
					153,
					255
				],
				[
					51,
					153,
					255
				],
				[
					51,
					153,
					255
				],
				[
					0,
					255,
					0
				],
				[
					255,
					128,
					0
				],
				[
					0,
					255,
					0
				],
				[
					255,
					128,
					0
				],
				[
					0,
					255,
					0
				],
				[
					255,
					128,
					0
				],
				[
					0,
					255,
					0
				],
				[
					255,
					128,
					0
				],
				[
					0,
					255,
					0
				],
				[
					255,
					128,
					0
				],
				[
					0,
					255,
					0
				],
				[
					255,
					128,
					0
				]
			],
			"dtype": "uint8",
			"shape": [
				17,
				3
			],
			"Corder": true
		},
		"num_skeleton_links": 19,
		"skeleton_links": [
			[
				15,
				13
			],
			[
				13,
				11
			],
			[
				16,
				14
			],
			[
				14,
				12
			],
			[
				11,
				12
			],
			[
				5,
				11
			],
			[
				6,
				12
			],
			[
				5,
				6
			],
			[
				5,
				7
			],
			[
				6,
				8
			],
			[
				7,
				9
			],
			[
				8,
				10
			],
			[
				1,
				2
			],
			[
				0,
				1
			],
			[
				0,
				2
			],
			[
				1,
				3
			],
			[
				2,
				4
			],
			[
				3,
				5
			],
			[
				4,
				6
			]
		],
		"skeleton_link_colors": {
			"__ndarray__": [
				[
					0,
					255,
					0
				],
				[
					0,
					255,
					0
				],
				[
					255,
					128,
					0
				],
				[
					255,
					128,
					0
				],
				[
					51,
					153,
					255
				],
				[
					51,
					153,
					255
				],
				[
					51,
					153,
					255
				],
				[
					51,
					153,
					255
				],
				[
					0,
					255,
					0
				],
				[
					255,
					128,
					0
				],
				[
					0,
					255,
					0
				],
				[
					255,
					128,
					0
				],
				[
					51,
					153,
					255
				],
				[
					51,
					153,
					255
				],
				[
					51,
					153,
					255
				],
				[
					51,
					153,
					255
				],
				[
					51,
					153,
					255
				],
				[
					51,
					153,
					255
				],
				[
					51,
					153,
					255
				]
			],
			"dtype": "uint8",
			"shape": [
				19,
				3
			],
			"Corder": true
		},
		"dataset_keypoint_weights": {
			"__ndarray__": [
				1.0,
				1.0,
				1.0,
				1.0,
				1.0,
				1.0,
				1.0,
				1.2000000476837158,
				1.2000000476837158,
				1.5,
				1.5,
				1.0,
				1.0,
				1.2000000476837158,
				1.2000000476837158,
				1.5,
				1.5
			],
			"dtype": "float32",
			"shape": [
				17
			]
		},
		"sigmas": {
			"__ndarray__": [
				0.026000000536441803,
				0.02500000037252903,
				0.02500000037252903,
				0.03500000014901161,
				0.03500000014901161,
				0.07900000363588333,
				0.07900000363588333,
				0.07199999690055847,
				0.07199999690055847,
				0.06199999898672104,
				0.06199999898672104,
				0.10700000077486038,
				0.10700000077486038,
				0.08699999749660492,
				0.08699999749660492,
				0.08900000154972076,
				0.08900000154972076
			],
			"dtype": "float32",
			"shape": [
				17
			]
		}
	},
	"instance_info": [
		{
			"frame_id": 1,
			"instances": [
				{
					"keypoints": [
						[
							646.4089965820312,
							5.5368523597717285
						],
						[
							649.587890625,
							-10.357845306396484
						],
						[
							633.6932373046875,
							-18.305192947387695
						],
						[
							589.1880493164062,
							-13.536784172058105
						],
						[
							586.0091552734375,
							-29.431482315063477
						],
						[
							504.9461669921875,
							38.91571807861328
						],
						[
							560.57763671875,
							30.968368530273438
						],
						[
							592.3670043945312,
							259.8520202636719
						],
						[
							646.4089965820312,
							232.83102416992188
						],
						[
							721.1140747070312,
							363.16754150390625
						],
						[
							783.1033935546875,
							359.9886169433594
						],
						[
							584.419677734375,
							361.57806396484375
						],
						[
							557.398681640625,
							377.4727783203125
						],
						[
							762.4402465820312,
							444.2304992675781
						],
						[
							681.3773193359375,
							596.819580078125
						],
						[
							635.28271484375,
							627.01953125
						],
						[
							625.745849609375,
							859.0820922851562
						]
					],
					"keypoint_scores": [
						0.6745622754096985,
						0.3025094270706177,
						0.39992618560791016,
						0.28703510761260986,
						0.3665745258331299,
						0.6370143294334412,
						0.7949713468551636,
						0.590653657913208,
						0.7888494729995728,
						0.5838714241981506,
						0.7828189134597778,
						0.5955377817153931,
						0.6996210813522339,
						0.8103811144828796,
						0.8195270895957947,
						0.6266260743141174,
						0.8145501613616943
					],
					"bbox": [
						[
							415.277587890625,
							0.4505767822265625,
							893.4351196289062,
							977.020751953125
						]
					],
					"bbox_score": 0.8738629221916199
				}
			]
		}
	]
}