{
	"meta_info": {
		"dataset_name": "halpe",
		"num_keypoints": 26,
		"keypoint_id2name": {
			"0": "nose",
			"1": "left_eye",
			"2": "right_eye",
			"3": "left_ear",
			"4": "right_ear",
			"5": "left_shoulder",
			"6": "right_shoulder",
			"7": "left_elbow",
			"8": "right_elbow",
			"9": "left_wrist",
			"10": "right_wrist",
			"11": "left_hip",
			"12": "right_hip",
			"13": "left_knee",
			"14": "right_knee",
			"15": "left_ankle",
			"16": "right_ankle",
			"17": "head",
			"18": "neck",
			"19": "hip",
			"20": "left_big_toe",
			"21": "right_big_toe",
			"22": "left_small_toe",
			"23": "right_small_toe",
			"24": "left_heel",
			"25": "right_heel"
		},
		"keypoint_name2id": {
			"nose": 0,
			"left_eye": 1,
			"right_eye": 2,
			"left_ear": 3,
			"right_ear": 4,
			"left_shoulder": 5,
			"right_shoulder": 6,
			"left_elbow": 7,
			"right_elbow": 8,
			"left_wrist": 9,
			"right_wrist": 10,
			"left_hip": 11,
			"right_hip": 12,
			"left_knee": 13,
			"right_knee": 14,
			"left_ankle": 15,
			"right_ankle": 16,
			"head": 17,
			"neck": 18,
			"hip": 19,
			"left_big_toe": 20,
			"right_big_toe": 21,
			"left_small_toe": 22,
			"right_small_toe": 23,
			"left_heel": 24,
			"right_heel": 25
		},
		"upper_body_ids": [
			0,
			1,
			2,
			3,
			4,
			5,
			6,
			7,
			8,
			9,
			10,
			17,
			18
		],
		"lower_body_ids": [
			11,
			12,
			13,
			14,
			15,
			16,
			19,
			20,
			21,
			22,
			23,
			24,
			25
		],
		"flip_indices": [
			0,
			2,
			1,
			4,
			3,
			6,
			5,
			8,
			7,
			10,
			9,
			12,
			11,
			14,
			13,
			16,
			15,
			17,
			18,
			19,
			21,
			20,
			23,
			22,
			25,
			24
		],
		"flip_pairs": [
			[
				2,
				1
			],
			[
				1,
				2
			],
			[
				4,
				3
			],
			[
				3,
				4
			],
			[
				6,
				5
			],
			[
				5,
				6
			],
			[
				8,
				7
			],
			[
				7,
				8
			],
			[
				10,
				9
			],
			[
				9,
				10
			],
			[
				12,
				11
			],
			[
				11,
				12
			],
			[
				14,
				13
			],
			[
				13,
				14
			],
			[
				16,
				15
			],
			[
				15,
				16
			],
			[
				21,
				20
			],
			[
				20,
				21
			],
			[
				23,
				22
			],
			[
				22,
				23
			],
			[
				25,
				24
			],
			[
				24,
				25
			]
		],
		"keypoint_colors": {
			"__ndarray__": [
				[
					51,
					153,
					255
				],
				[
					51,
					153,
					255
				],
				[
					51,
					153,
					255
				],
				[
					51,
					153,
					255
				],
				[
					51,
					153,
					255
				],
				[
					0,
					255,
					0
				],
				[
					255,
					128,
					0
				],
				[
					0,
					255,
					0
				],
				[
					255,
					128,
					0
				],
				[
					0,
					255,
					0
				],
				[
					255,
					128,
					0
				],
				[
					0,
					255,
					0
				],
				[
					255,
					128,
					0
				],
				[
					0,
					255,
					0
				],
				[
					255,
					128,
					0
				],
				[
					0,
					255,
					0
				],
				[
					255,
					128,
					0
				],
				[
					255,
					128,
					0
				],
				[
					255,
					128,
					0
				],
				[
					255,
					128,
					0
				],
				[
					255,
					128,
					0
				],
				[
					255,
					128,
					0
				],
				[
					255,
					128,
					0
				],
				[
					255,
					128,
					0
				],
				[
					255,
					128,
					0
				],
				[
					255,
					128,
					0
				]
			],
			"dtype": "uint8",
			"shape": [
				26,
				3
			],
			"Corder": true
		},
		"num_skeleton_links": 27,
		"skeleton_links": [
			[
				15,
				13
			],
			[
				13,
				11
			],
			[
				11,
				19
			],
			[
				16,
				14
			],
			[
				14,
				12
			],
			[
				12,
				19
			],
			[
				17,
				18
			],
			[
				18,
				19
			],
			[
				18,
				5
			],
			[
				5,
				7
			],
			[
				7,
				9
			],
			[
				18,
				6
			],
			[
				6,
				8
			],
			[
				8,
				10
			],
			[
				1,
				2
			],
			[
				0,
				1
			],
			[
				0,
				2
			],
			[
				1,
				3
			],
			[
				2,
				4
			],
			[
				3,
				5
			],
			[
				4,
				6
			],
			[
				15,
				20
			],
			[
				15,
				22
			],
			[
				15,
				24
			],
			[
				16,
				21
			],
			[
				16,
				23
			],
			[
				16,
				25
			]
		],
		"skeleton_link_colors": {
			"__ndarray__": [
				[
					0,
					255,
					0
				],
				[
					0,
					255,
					0
				],
				[
					0,
					255,
					0
				],
				[
					255,
					128,
					0
				],
				[
					255,
					128,
					0
				],
				[
					255,
					128,
					0
				],
				[
					51,
					153,
					255
				],
				[
					51,
					153,
					255
				],
				[
					0,
					255,
					0
				],
				[
					0,
					255,
					0
				],
				[
					0,
					255,
					0
				],
				[
					255,
					128,
					0
				],
				[
					255,
					128,
					0
				],
				[
					255,
					128,
					0
				],
				[
					51,
					153,
					255
				],
				[
					51,
					153,
					255
				],
				[
					51,
					153,
					255
				],
				[
					51,
					153,
					255
				],
				[
					51,
					153,
					255
				],
				[
					51,
					153,
					255
				],
				[
					51,
					153,
					255
				],
				[
					0,
					255,
					0
				],
				[
					0,
					255,
					0
				],
				[
					0,
					255,
					0
				],
				[
					255,
					128,
					0
				],
				[
					255,
					128,
					0
				],
				[
					255,
					128,
					0
				]
			],
			"dtype": "uint8",
			"shape": [
				27,
				3
			],
			"Corder": true
		},
		"dataset_keypoint_weights": {
			"__ndarray__": [
				1.0,
				1.0,
				1.0,
				1.0,
				1.0,
				1.0,
				1.0,
				1.2000000476837158,
				1.2000000476837158,
				1.5,
				1.5,
				1.0,
				1.0,
				1.2000000476837158,
				1.2000000476837158,
				1.5,
				1.5,
				1.0,
				1.0,
				1.2000000476837158,
				1.5,
				1.5,
				1.5,
				1.5,
				1.5,
				1.5
			],
			"dtype": "float32",
			"shape": [
				26
			]
		},
		"sigmas": {
			"__ndarray__": [
				0.026000000536441803,
				0.02500000037252903,
				0.02500000037252903,
				0.03500000014901161,
				0.03500000014901161,
				0.07900000363588333,
				0.07900000363588333,
				0.07199999690055847,
				0.07199999690055847,
				0.06199999898672104,
				0.06199999898672104,
				0.10700000077486038,
				0.10700000077486038,
				0.08699999749660492,
				0.08699999749660492,
				0.08900000154972076,
				0.08900000154972076,
				0.026000000536441803,
				0.026000000536441803,
				0.06599999964237213,
				0.07900000363588333,
				0.07900000363588333,
				0.07900000363588333,
				0.07900000363588333,
				0.07900000363588333,
				0.07900000363588333
			],
			"dtype": "float32",
			"shape": [
				26
			]
		}
	},
	"instance_info": [
		{
			"frame_id": 1,
			"instances": [
				{
					"keypoints": [
						[
							808.7039794921875,
							96.03268432617188
						],
						[
							817.3724365234375,
							71.47222900390625
						],
						[
							807.25927734375,
							77.25115966796875
						],
						[
							880.940673828125,
							65.69329833984375
						],
						[
							888.164306640625,
							72.91696166992188
						],
						[
							960.4009399414062,
							137.929931640625
						],
						[
							938.72998046875,
							162.49038696289062
						],
						[
							870.8275146484375,
							296.85052490234375
						],
						[
							886.7196044921875,
							335.8583068847656
						],
						[
							729.2437133789062,
							390.7581481933594
						],
						[
							765.362060546875,
							423.98699951171875
						],
						[
							1156.884521484375,
							382.0897521972656
						],
						[
							1143.8819580078125,
							384.9792175292969
						],
						[
							958.9561767578125,
							517.8946533203125
						],
						[
							974.8482666015625,
							541.0103759765625
						],
						[
							990.7403564453125,
							776.5017700195312
						],
						[
							1101.9847412109375,
							715.822998046875
						],
						[
							837.5986328125,
							15.127655029296875
						],
						[
							911.280029296875,
							123.48260498046875
						],
						[
							1158.329345703125,
							369.087158203125
						],
						[
							875.1617431640625,
							829.9569091796875
						],
						[
							1057.197998046875,
							827.0673828125
						],
						[
							895.387939453125,
							840.0700073242188
						],
						[
							1064.421630859375,
							818.3990478515625
						],
						[
							1009.5218505859375,
							816.9542846679688
						],
						[
							1149.660888671875,
							727.380859375
						]
					],
					"keypoint_scores": [
						0.9166797399520874,
						1.0007437467575073,
						0.8853229284286499,
						0.9160803556442261,
						0.4087364673614502,
						0.7173576951026917,
						0.617466926574707,
						0.7822399139404297,
						0.720569372177124,
						0.847602367401123,
						0.765056848526001,
						0.6812115907669067,
						0.6135556697845459,
						0.7455987930297852,
						0.6432980298995972,
						0.7943030595779419,
						0.6998170614242554,
						0.7346011400222778,
						0.7718696594238281,
						0.8858678936958313,
						0.7177391648292542,
						0.6547414064407349,
						0.6842131614685059,
						0.5606751441955566,
						0.7782635688781738,
						0.7329620122909546
					],
					"bbox": [
						[
							639.960205078125,
							0.3913421630859375,
							1246.1680908203125,
							888.03515625
						]
					],
					"bbox_score": 0.875296413898468
				}
			]
		}
	]
}