{
	"meta_info": {
		"dataset_name": "coco",
		"num_keypoints": 17,
		"keypoint_id2name": {
			"0": "nose",
			"1": "left_eye",
			"2": "right_eye",
			"3": "left_ear",
			"4": "right_ear",
			"5": "left_shoulder",
			"6": "right_shoulder",
			"7": "left_elbow",
			"8": "right_elbow",
			"9": "left_wrist",
			"10": "right_wrist",
			"11": "left_hip",
			"12": "right_hip",
			"13": "left_knee",
			"14": "right_knee",
			"15": "left_ankle",
			"16": "right_ankle"
		},
		"keypoint_name2id": {
			"nose": 0,
			"left_eye": 1,
			"right_eye": 2,
			"left_ear": 3,
			"right_ear": 4,
			"left_shoulder": 5,
			"right_shoulder": 6,
			"left_elbow": 7,
			"right_elbow": 8,
			"left_wrist": 9,
			"right_wrist": 10,
			"left_hip": 11,
			"right_hip": 12,
			"left_knee": 13,
			"right_knee": 14,
			"left_ankle": 15,
			"right_ankle": 16
		},
		"upper_body_ids": [
			0,
			1,
			2,
			3,
			4,
			5,
			6,
			7,
			8,
			9,
			10
		],
		"lower_body_ids": [
			11,
			12,
			13,
			14,
			15,
			16
		],
		"flip_indices": [
			0,
			2,
			1,
			4,
			3,
			6,
			5,
			8,
			7,
			10,
			9,
			12,
			11,
			14,
			13,
			16,
			15
		],
		"flip_pairs": [
			[
				2,
				1
			],
			[
				1,
				2
			],
			[
				4,
				3
			],
			[
				3,
				4
			],
			[
				6,
				5
			],
			[
				5,
				6
			],
			[
				8,
				7
			],
			[
				7,
				8
			],
			[
				10,
				9
			],
			[
				9,
				10
			],
			[
				12,
				11
			],
			[
				11,
				12
			],
			[
				14,
				13
			],
			[
				13,
				14
			],
			[
				16,
				15
			],
			[
				15,
				16
			]
		],
		"keypoint_colors": {
			"__ndarray__": [
				[
					51,
					153,
					255
				],
				[
					51,
					153,
					255
				],
				[
					51,
					153,
					255
				],
				[
					51,
					153,
					255
				],
				[
					51,
					153,
					255
				],
				[
					0,
					255,
					0
				],
				[
					255,
					128,
					0
				],
				[
					0,
					255,
					0
				],
				[
					255,
					128,
					0
				],
				[
					0,
					255,
					0
				],
				[
					255,
					128,
					0
				],
				[
					0,
					255,
					0
				],
				[
					255,
					128,
					0
				],
				[
					0,
					255,
					0
				],
				[
					255,
					128,
					0
				],
				[
					0,
					255,
					0
				],
				[
					255,
					128,
					0
				]
			],
			"dtype": "uint8",
			"shape": [
				17,
				3
			],
			"Corder": true
		},
		"num_skeleton_links": 19,
		"skeleton_links": [
			[
				15,
				13
			],
			[
				13,
				11
			],
			[
				16,
				14
			],
			[
				14,
				12
			],
			[
				11,
				12
			],
			[
				5,
				11
			],
			[
				6,
				12
			],
			[
				5,
				6
			],
			[
				5,
				7
			],
			[
				6,
				8
			],
			[
				7,
				9
			],
			[
				8,
				10
			],
			[
				1,
				2
			],
			[
				0,
				1
			],
			[
				0,
				2
			],
			[
				1,
				3
			],
			[
				2,
				4
			],
			[
				3,
				5
			],
			[
				4,
				6
			]
		],
		"skeleton_link_colors": {
			"__ndarray__": [
				[
					0,
					255,
					0
				],
				[
					0,
					255,
					0
				],
				[
					255,
					128,
					0
				],
				[
					255,
					128,
					0
				],
				[
					51,
					153,
					255
				],
				[
					51,
					153,
					255
				],
				[
					51,
					153,
					255
				],
				[
					51,
					153,
					255
				],
				[
					0,
					255,
					0
				],
				[
					255,
					128,
					0
				],
				[
					0,
					255,
					0
				],
				[
					255,
					128,
					0
				],
				[
					51,
					153,
					255
				],
				[
					51,
					153,
					255
				],
				[
					51,
					153,
					255
				],
				[
					51,
					153,
					255
				],
				[
					51,
					153,
					255
				],
				[
					51,
					153,
					255
				],
				[
					51,
					153,
					255
				]
			],
			"dtype": "uint8",
			"shape": [
				19,
				3
			],
			"Corder": true
		},
		"dataset_keypoint_weights": {
			"__ndarray__": [
				1.0,
				1.0,
				1.0,
				1.0,
				1.0,
				1.0,
				1.0,
				1.2000000476837158,
				1.2000000476837158,
				1.5,
				1.5,
				1.0,
				1.0,
				1.2000000476837158,
				1.2000000476837158,
				1.5,
				1.5
			],
			"dtype": "float32",
			"shape": [
				17
			]
		},
		"sigmas": {
			"__ndarray__": [
				0.026000000536441803,
				0.02500000037252903,
				0.02500000037252903,
				0.03500000014901161,
				0.03500000014901161,
				0.07900000363588333,
				0.07900000363588333,
				0.07199999690055847,
				0.07199999690055847,
				0.06199999898672104,
				0.06199999898672104,
				0.10700000077486038,
				0.10700000077486038,
				0.08699999749660492,
				0.08699999749660492,
				0.08900000154972076,
				0.08900000154972076
			],
			"dtype": "float32",
			"shape": [
				17
			]
		}
	},
	"instance_info": [
		{
			"frame_id": 1,
			"instances": [
				{
					"keypoints": [
						[
							819.4596557617188,
							154.03573608398438
						],
						[
							817.127197265625,
							128.37855529785156
						],
						[
							805.46484375,
							142.37338256835938
						],
						[
							866.1090698242188,
							88.72657012939453
						],
						[
							842.7843627929688,
							137.70843505859375
						],
						[
							957.075439453125,
							137.70843505859375
						],
						[
							931.4182739257812,
							168.03054809570312
						],
						[
							870.7740478515625,
							296.31640625
						],
						[
							877.7714233398438,
							335.9684143066406
						],
						[
							728.4933471679688,
							389.615234375
						],
						[
							772.810302734375,
							422.2698059082031
						],
						[
							1157.6678466796875,
							375.6203918457031
						],
						[
							1094.691162109375,
							375.6203918457031
						],
						[
							1043.3768310546875,
							601.8699951171875
						],
						[
							919.7559204101562,
							454.92437744140625
						],
						[
							1057.3717041015625,
							856.1092529296875
						],
						[
							1045.7093505859375,
							660.1817626953125
						]
					],
					"keypoint_scores": [
						0.9035556316375732,
						0.9232169985771179,
						0.8788480758666992,
						0.9254973530769348,
						0.3260503113269806,
						0.8322982788085938,
						0.6577110290527344,
						0.8032547235488892,
						0.6383171081542969,
						0.7811523675918579,
						0.7506124973297119,
						0.7803247570991516,
						0.7014439702033997,
						0.891258716583252,
						0.7927819490432739,
						0.8863943815231323,
						0.6810369491577148
					],
					"bbox": [
						[
							637.2894287109375,
							12.221580505371094,
							1234.876953125,
							967.601318359375
						]
					],
					"bbox_score": 0.8703835606575012
				}
			]
		}
	]
}